harmonydagger/__init__.py
harmonydagger/__main__.py
harmonydagger/audio.py
harmonydagger/cli.py
harmonydagger/common.py
harmonydagger/core.py
harmonydagger/file_operations.py
harmonydagger/psychoacoustics.py
harmonydagger/visualization.py
harmonydagger/wav_utils.py
harmonydagger-0.3.5.dist-info/licenses/LICENSE
harmonydagger-0.3.5.dist-info/METADATA
harmonydagger-0.3.5.dist-info/WHEEL
harmonydagger-0.3.5.dist-info/entry_points.txt
harmonydagger-0.3.5.dist-info/top_level.txt
harmonydagger-0.3.5.dist-info/RECORD
